<?xml version="1.0" encoding="utf-8"?>
<!DOCTYPE hibernate-mapping PUBLIC "-//Hibernate/Hibernate Mapping DTD 3.0//EN"
"http://www.hibernate.org/dtd/hibernate-mapping-3.0.dtd">
<!-- 
    Mapping file autogenerated by MyEclipse Persistence Tools
-->
<hibernate-mapping>
    <class name="org.vo.Students" table="students" catalog="mybook">
        <id name="readerId" type="java.lang.String">
            <column name="readerId" />
            <generator class="assigned" />
        </id>
        <property name="name" type="java.lang.String">
            <column name="name" />
        </property>
        <property name="spec" type="java.lang.String">
            <column name="spec" />
        </property>
        <property name="sex" type="java.lang.Integer">
            <column name="sex" />
        </property>
        <property name="born" type="java.util.Date">
            <column name="born" length="10" />
        </property>
        <property name="num" type="java.lang.Integer">
            <column name="num" />
        </property>
    </class>
</hibernate-mapping>
